salesforce/__init__.py
salesforce/decorators.py
salesforce/salesforce.py
salesforce/custom_exceptions/__init__.py
salesforce/custom_exceptions/salesforce_exceptions.py
salesforce/utilities/__init__.py
salesforce/utilities/async_utils.py
salesforce/utilities/df_utils.py
salesforce/utilities/sf_query_processors.py
utilities/__init__.py
utilities/async_utils.py
veevanetwork/__init__.py
veevanetwork/api.py
veevanetwork/network_api_v25.json
veevanetwork/veevanetwork.py
veevanetwork/custom_exceptions/__init__.py
veevanetwork/custom_exceptions/veevanetwork_exceptions.py
veevanetwork/utilities/__init__.py
veevanetwork/utilities/async_utils.py
veevanitro/__init__.py
veevanitro/veevanitro.py
veevanitro/nitro_utils/__init__.py
veevanitro/nitro_utils/async_utils.py
veevanitro/nitro_utils/s3_utils.py
veevatools/__init__.py
veevatools/salesforce/__init__.py
veevatools-0.1.33.dist-info/licenses/LICENSE.txt
veevavault/__init__.py
veevavault/client/__init__.py
veevavault/client/vault_client.py
veevavault/utilities/__init__.py
veevavault/utilities/async_utils.py
veevatools-0.1.33.dist-info/METADATA
veevatools-0.1.33.dist-info/WHEEL
veevatools-0.1.33.dist-info/top_level.txt
veevatools-0.1.33.dist-info/RECORD
