Metadata-Version: 2.4
Name: veevatools
Version: 0.1.33
Summary: Veeva tools library for accelerating Veeva Systems Internal Tools development
Home-page: https://github.com/michaelpay
Author: Michael Pay
Author-email: monickenish@gmail.com
License-File: LICENSE.txt
Requires-Dist: pandas>=1.4.2
Requires-Dist: simple-salesforce>=1.11.6
Requires-Dist: salesforce-bulk>=2.2.0
Requires-Dist: sfdclib>=0.2.26
Requires-Dist: openpyxl<4.0.0,>=3.1.2
Requires-Dist: zeep<5.0.0,>=4.1.0
Requires-Dist: aiosignal>=1.2.0
Requires-Dist: aiohttp<4.0.0,>=3.11.12
Requires-Dist: pyarrow<20.0.0,>=19.0.0
Requires-Dist: psycopg2-binary<3.0.0,>=2.9.9
Requires-Dist: beautifulsoup4<5.0.0,>=4.11.1
Requires-Dist: boto3<2.0.0,>=1.26.15
Dynamic: license-file
